local_share/__init__.py
local_share/main.py
local_share/template.html
local_share_cli-0.1.7.dist-info/METADATA
local_share_cli-0.1.7.dist-info/WHEEL
local_share_cli-0.1.7.dist-info/entry_points.txt
local_share_cli-0.1.7.dist-info/top_level.txt
local_share_cli-0.1.7.dist-info/RECORD
