Metadata-Version: 2.4
Name: local-share-cli
Version: 0.1.7
Summary: Share files instantly over LAN with a QR code. Only one file at a time. Also, you can edit the 'template.html' file to customize your download page!
Requires-Python: >=3.8
Requires-Dist: qrcode[pil]
